pysnip.cpython-310-aarch64-linux-gnu.so
pysnip.pyi
PySnip_z7-7.3.2201261049.dist-info/METADATA
PySnip_z7-7.3.2201261049.dist-info/entry_points.txt
PySnip_z7-7.3.2201261049.dist-info/WHEEL
PySnip_z7-7.3.2201261049.dist-info/top_level.txt
PySnip_z7-7.3.2201261049.dist-info/zip-safe
PySnip_z7-7.3.2201261049.dist-info/RECORD
